{
  "directed": true,
  "multigraph": false,
  "graph": {},
  "nodes": [
    {
      "path": ".pre-commit-config.yaml",
      "language": "yaml",
      "purpose_statement": null,
      "domain_cluster": null,
      "complexity_score": 0.0,
      "change_velocity_30d": 0,
      "is_dead_code_candidate": true,
      "last_modified": null,
      "loc": 0,
      "imports": [],
      "exports": [],
      "docstring": null,
      "doc_drift_flag": false,
      "decorators": [],
      "node_type": "module",
      "id": ".pre-commit-config.yaml"
    },
    {
      "path": "dbt_project.yml",
      "language": "yaml",
      "purpose_statement": null,
      "domain_cluster": null,
      "complexity_score": 0.0,
      "change_velocity_30d": 0,
      "is_dead_code_candidate": true,
      "last_modified": null,
      "loc": 0,
      "imports": [],
      "exports": [],
      "docstring": null,
      "doc_drift_flag": false,
      "decorators": [],
      "node_type": "module",
      "id": "dbt_project.yml"
    },
    {
      "path": "macros/cents_to_dollars.sql",
      "language": "sql",
      "purpose_statement": null,
      "domain_cluster": null,
      "complexity_score": 0.0,
      "change_velocity_30d": 0,
      "is_dead_code_candidate": true,
      "last_modified": null,
      "loc": 0,
      "imports": [],
      "exports": [],
      "docstring": null,
      "doc_drift_flag": false,
      "decorators": [],
      "node_type": "module",
      "id": "macros/cents_to_dollars.sql"
    },
    {
      "path": "macros/generate_schema_name.sql",
      "language": "sql",
      "purpose_statement": null,
      "domain_cluster": null,
      "complexity_score": 0.0,
      "change_velocity_30d": 0,
      "is_dead_code_candidate": true,
      "last_modified": null,
      "loc": 0,
      "imports": [],
      "exports": [],
      "docstring": null,
      "doc_drift_flag": false,
      "decorators": [],
      "node_type": "module",
      "id": "macros/generate_schema_name.sql"
    },
    {
      "path": "models/marts/customers.sql",
      "language": "sql",
      "purpose_statement": null,
      "domain_cluster": null,
      "complexity_score": 0.0,
      "change_velocity_30d": 0,
      "is_dead_code_candidate": true,
      "last_modified": null,
      "loc": 0,
      "imports": [],
      "exports": [],
      "docstring": null,
      "doc_drift_flag": false,
      "decorators": [],
      "node_type": "module",
      "id": "models/marts/customers.sql"
    },
    {
      "path": "models/marts/customers.yml",
      "language": "yaml",
      "purpose_statement": null,
      "domain_cluster": null,
      "complexity_score": 0.0,
      "change_velocity_30d": 0,
      "is_dead_code_candidate": true,
      "last_modified": null,
      "loc": 0,
      "imports": [],
      "exports": [],
      "docstring": null,
      "doc_drift_flag": false,
      "decorators": [],
      "node_type": "module",
      "id": "models/marts/customers.yml"
    },
    {
      "path": "models/marts/locations.sql",
      "language": "sql",
      "purpose_statement": null,
      "domain_cluster": null,
      "complexity_score": 0.0,
      "change_velocity_30d": 0,
      "is_dead_code_candidate": true,
      "last_modified": null,
      "loc": 0,
      "imports": [],
      "exports": [],
      "docstring": null,
      "doc_drift_flag": false,
      "decorators": [],
      "node_type": "module",
      "id": "models/marts/locations.sql"
    },
    {
      "path": "models/marts/locations.yml",
      "language": "yaml",
      "purpose_statement": null,
      "domain_cluster": null,
      "complexity_score": 0.0,
      "change_velocity_30d": 0,
      "is_dead_code_candidate": true,
      "last_modified": null,
      "loc": 0,
      "imports": [],
      "exports": [],
      "docstring": null,
      "doc_drift_flag": false,
      "decorators": [],
      "node_type": "module",
      "id": "models/marts/locations.yml"
    },
    {
      "path": "models/marts/metricflow_time_spine.sql",
      "language": "sql",
      "purpose_statement": null,
      "domain_cluster": null,
      "complexity_score": 0.0,
      "change_velocity_30d": 0,
      "is_dead_code_candidate": true,
      "last_modified": null,
      "loc": 0,
      "imports": [],
      "exports": [],
      "docstring": null,
      "doc_drift_flag": false,
      "decorators": [],
      "node_type": "module",
      "id": "models/marts/metricflow_time_spine.sql"
    },
    {
      "path": "models/marts/order_items.sql",
      "language": "sql",
      "purpose_statement": null,
      "domain_cluster": null,
      "complexity_score": 0.0,
      "change_velocity_30d": 0,
      "is_dead_code_candidate": true,
      "last_modified": null,
      "loc": 0,
      "imports": [],
      "exports": [],
      "docstring": null,
      "doc_drift_flag": false,
      "decorators": [],
      "node_type": "module",
      "id": "models/marts/order_items.sql"
    },
    {
      "path": "models/marts/order_items.yml",
      "language": "yaml",
      "purpose_statement": null,
      "domain_cluster": null,
      "complexity_score": 0.0,
      "change_velocity_30d": 0,
      "is_dead_code_candidate": true,
      "last_modified": null,
      "loc": 0,
      "imports": [],
      "exports": [],
      "docstring": null,
      "doc_drift_flag": false,
      "decorators": [],
      "node_type": "module",
      "id": "models/marts/order_items.yml"
    },
    {
      "path": "models/marts/orders.sql",
      "language": "sql",
      "purpose_statement": null,
      "domain_cluster": null,
      "complexity_score": 0.0,
      "change_velocity_30d": 0,
      "is_dead_code_candidate": true,
      "last_modified": null,
      "loc": 0,
      "imports": [],
      "exports": [],
      "docstring": null,
      "doc_drift_flag": false,
      "decorators": [],
      "node_type": "module",
      "id": "models/marts/orders.sql"
    },
    {
      "path": "models/marts/orders.yml",
      "language": "yaml",
      "purpose_statement": null,
      "domain_cluster": null,
      "complexity_score": 0.0,
      "change_velocity_30d": 0,
      "is_dead_code_candidate": true,
      "last_modified": null,
      "loc": 0,
      "imports": [],
      "exports": [],
      "docstring": null,
      "doc_drift_flag": false,
      "decorators": [],
      "node_type": "module",
      "id": "models/marts/orders.yml"
    },
    {
      "path": "models/marts/products.sql",
      "language": "sql",
      "purpose_statement": null,
      "domain_cluster": null,
      "complexity_score": 0.0,
      "change_velocity_30d": 0,
      "is_dead_code_candidate": true,
      "last_modified": null,
      "loc": 0,
      "imports": [],
      "exports": [],
      "docstring": null,
      "doc_drift_flag": false,
      "decorators": [],
      "node_type": "module",
      "id": "models/marts/products.sql"
    },
    {
      "path": "models/marts/products.yml",
      "language": "yaml",
      "purpose_statement": null,
      "domain_cluster": null,
      "complexity_score": 0.0,
      "change_velocity_30d": 0,
      "is_dead_code_candidate": true,
      "last_modified": null,
      "loc": 0,
      "imports": [],
      "exports": [],
      "docstring": null,
      "doc_drift_flag": false,
      "decorators": [],
      "node_type": "module",
      "id": "models/marts/products.yml"
    },
    {
      "path": "models/marts/supplies.sql",
      "language": "sql",
      "purpose_statement": null,
      "domain_cluster": null,
      "complexity_score": 0.0,
      "change_velocity_30d": 0,
      "is_dead_code_candidate": true,
      "last_modified": null,
      "loc": 0,
      "imports": [],
      "exports": [],
      "docstring": null,
      "doc_drift_flag": false,
      "decorators": [],
      "node_type": "module",
      "id": "models/marts/supplies.sql"
    },
    {
      "path": "models/marts/supplies.yml",
      "language": "yaml",
      "purpose_statement": null,
      "domain_cluster": null,
      "complexity_score": 0.0,
      "change_velocity_30d": 0,
      "is_dead_code_candidate": true,
      "last_modified": null,
      "loc": 0,
      "imports": [],
      "exports": [],
      "docstring": null,
      "doc_drift_flag": false,
      "decorators": [],
      "node_type": "module",
      "id": "models/marts/supplies.yml"
    },
    {
      "path": "models/staging/__sources.yml",
      "language": "yaml",
      "purpose_statement": null,
      "domain_cluster": null,
      "complexity_score": 0.0,
      "change_velocity_30d": 0,
      "is_dead_code_candidate": true,
      "last_modified": null,
      "loc": 0,
      "imports": [],
      "exports": [],
      "docstring": null,
      "doc_drift_flag": false,
      "decorators": [],
      "node_type": "module",
      "id": "models/staging/__sources.yml"
    },
    {
      "path": "models/staging/stg_customers.sql",
      "language": "sql",
      "purpose_statement": null,
      "domain_cluster": null,
      "complexity_score": 0.0,
      "change_velocity_30d": 0,
      "is_dead_code_candidate": true,
      "last_modified": null,
      "loc": 0,
      "imports": [],
      "exports": [],
      "docstring": null,
      "doc_drift_flag": false,
      "decorators": [],
      "node_type": "module",
      "id": "models/staging/stg_customers.sql"
    },
    {
      "path": "models/staging/stg_customers.yml",
      "language": "yaml",
      "purpose_statement": null,
      "domain_cluster": null,
      "complexity_score": 0.0,
      "change_velocity_30d": 0,
      "is_dead_code_candidate": true,
      "last_modified": null,
      "loc": 0,
      "imports": [],
      "exports": [],
      "docstring": null,
      "doc_drift_flag": false,
      "decorators": [],
      "node_type": "module",
      "id": "models/staging/stg_customers.yml"
    },
    {
      "path": "models/staging/stg_locations.sql",
      "language": "sql",
      "purpose_statement": null,
      "domain_cluster": null,
      "complexity_score": 0.0,
      "change_velocity_30d": 0,
      "is_dead_code_candidate": true,
      "last_modified": null,
      "loc": 0,
      "imports": [],
      "exports": [],
      "docstring": null,
      "doc_drift_flag": false,
      "decorators": [],
      "node_type": "module",
      "id": "models/staging/stg_locations.sql"
    },
    {
      "path": "models/staging/stg_locations.yml",
      "language": "yaml",
      "purpose_statement": null,
      "domain_cluster": null,
      "complexity_score": 0.0,
      "change_velocity_30d": 0,
      "is_dead_code_candidate": true,
      "last_modified": null,
      "loc": 0,
      "imports": [],
      "exports": [],
      "docstring": null,
      "doc_drift_flag": false,
      "decorators": [],
      "node_type": "module",
      "id": "models/staging/stg_locations.yml"
    },
    {
      "path": "models/staging/stg_order_items.sql",
      "language": "sql",
      "purpose_statement": null,
      "domain_cluster": null,
      "complexity_score": 0.0,
      "change_velocity_30d": 0,
      "is_dead_code_candidate": true,
      "last_modified": null,
      "loc": 0,
      "imports": [],
      "exports": [],
      "docstring": null,
      "doc_drift_flag": false,
      "decorators": [],
      "node_type": "module",
      "id": "models/staging/stg_order_items.sql"
    },
    {
      "path": "models/staging/stg_order_items.yml",
      "language": "yaml",
      "purpose_statement": null,
      "domain_cluster": null,
      "complexity_score": 0.0,
      "change_velocity_30d": 0,
      "is_dead_code_candidate": true,
      "last_modified": null,
      "loc": 0,
      "imports": [],
      "exports": [],
      "docstring": null,
      "doc_drift_flag": false,
      "decorators": [],
      "node_type": "module",
      "id": "models/staging/stg_order_items.yml"
    },
    {
      "path": "models/staging/stg_orders.sql",
      "language": "sql",
      "purpose_statement": null,
      "domain_cluster": null,
      "complexity_score": 0.0,
      "change_velocity_30d": 0,
      "is_dead_code_candidate": true,
      "last_modified": null,
      "loc": 0,
      "imports": [],
      "exports": [],
      "docstring": null,
      "doc_drift_flag": false,
      "decorators": [],
      "node_type": "module",
      "id": "models/staging/stg_orders.sql"
    },
    {
      "path": "models/staging/stg_orders.yml",
      "language": "yaml",
      "purpose_statement": null,
      "domain_cluster": null,
      "complexity_score": 0.0,
      "change_velocity_30d": 0,
      "is_dead_code_candidate": true,
      "last_modified": null,
      "loc": 0,
      "imports": [],
      "exports": [],
      "docstring": null,
      "doc_drift_flag": false,
      "decorators": [],
      "node_type": "module",
      "id": "models/staging/stg_orders.yml"
    },
    {
      "path": "models/staging/stg_products.sql",
      "language": "sql",
      "purpose_statement": null,
      "domain_cluster": null,
      "complexity_score": 0.0,
      "change_velocity_30d": 0,
      "is_dead_code_candidate": true,
      "last_modified": null,
      "loc": 0,
      "imports": [],
      "exports": [],
      "docstring": null,
      "doc_drift_flag": false,
      "decorators": [],
      "node_type": "module",
      "id": "models/staging/stg_products.sql"
    },
    {
      "path": "models/staging/stg_products.yml",
      "language": "yaml",
      "purpose_statement": null,
      "domain_cluster": null,
      "complexity_score": 0.0,
      "change_velocity_30d": 0,
      "is_dead_code_candidate": true,
      "last_modified": null,
      "loc": 0,
      "imports": [],
      "exports": [],
      "docstring": null,
      "doc_drift_flag": false,
      "decorators": [],
      "node_type": "module",
      "id": "models/staging/stg_products.yml"
    },
    {
      "path": "models/staging/stg_supplies.sql",
      "language": "sql",
      "purpose_statement": null,
      "domain_cluster": null,
      "complexity_score": 0.0,
      "change_velocity_30d": 0,
      "is_dead_code_candidate": true,
      "last_modified": null,
      "loc": 0,
      "imports": [],
      "exports": [],
      "docstring": null,
      "doc_drift_flag": false,
      "decorators": [],
      "node_type": "module",
      "id": "models/staging/stg_supplies.sql"
    },
    {
      "path": "models/staging/stg_supplies.yml",
      "language": "yaml",
      "purpose_statement": null,
      "domain_cluster": null,
      "complexity_score": 0.0,
      "change_velocity_30d": 0,
      "is_dead_code_candidate": true,
      "last_modified": null,
      "loc": 0,
      "imports": [],
      "exports": [],
      "docstring": null,
      "doc_drift_flag": false,
      "decorators": [],
      "node_type": "module",
      "id": "models/staging/stg_supplies.yml"
    },
    {
      "path": "package-lock.yml",
      "language": "yaml",
      "purpose_statement": null,
      "domain_cluster": null,
      "complexity_score": 0.0,
      "change_velocity_30d": 0,
      "is_dead_code_candidate": true,
      "last_modified": null,
      "loc": 0,
      "imports": [],
      "exports": [],
      "docstring": null,
      "doc_drift_flag": false,
      "decorators": [],
      "node_type": "module",
      "id": "package-lock.yml"
    },
    {
      "path": "packages.yml",
      "language": "yaml",
      "purpose_statement": null,
      "domain_cluster": null,
      "complexity_score": 0.0,
      "change_velocity_30d": 0,
      "is_dead_code_candidate": true,
      "last_modified": null,
      "loc": 0,
      "imports": [],
      "exports": [],
      "docstring": null,
      "doc_drift_flag": false,
      "decorators": [],
      "node_type": "module",
      "id": "packages.yml"
    },
    {
      "path": "Taskfile.yml",
      "language": "yaml",
      "purpose_statement": null,
      "domain_cluster": null,
      "complexity_score": 0.0,
      "change_velocity_30d": 0,
      "is_dead_code_candidate": true,
      "last_modified": null,
      "loc": 0,
      "imports": [],
      "exports": [],
      "docstring": null,
      "doc_drift_flag": false,
      "decorators": [],
      "node_type": "module",
      "id": "Taskfile.yml"
    }
  ],
  "edges": [
    {
      "edge_type": "CONFIGURES",
      "weight": 1,
      "source": "dbt_project.yml",
      "target": "models/marts/products.sql"
    },
    {
      "edge_type": "CONFIGURES",
      "weight": 1,
      "source": "dbt_project.yml",
      "target": "macros/cents_to_dollars.sql"
    },
    {
      "edge_type": "CONFIGURES",
      "weight": 1,
      "source": "dbt_project.yml",
      "target": "models/marts/metricflow_time_spine.sql"
    },
    {
      "edge_type": "CONFIGURES",
      "weight": 1,
      "source": "dbt_project.yml",
      "target": "models/marts/locations.sql"
    },
    {
      "edge_type": "CONFIGURES",
      "weight": 1,
      "source": "dbt_project.yml",
      "target": "models/marts/customers.sql"
    },
    {
      "edge_type": "CONFIGURES",
      "weight": 1,
      "source": "dbt_project.yml",
      "target": "models/staging/stg_customers.sql"
    },
    {
      "edge_type": "CONFIGURES",
      "weight": 1,
      "source": "dbt_project.yml",
      "target": "models/staging/stg_order_items.sql"
    },
    {
      "edge_type": "CONFIGURES",
      "weight": 1,
      "source": "dbt_project.yml",
      "target": "models/marts/order_items.sql"
    },
    {
      "edge_type": "CONFIGURES",
      "weight": 1,
      "source": "dbt_project.yml",
      "target": "models/staging/stg_locations.sql"
    },
    {
      "edge_type": "CONFIGURES",
      "weight": 1,
      "source": "dbt_project.yml",
      "target": "models/marts/orders.sql"
    },
    {
      "edge_type": "CONFIGURES",
      "weight": 1,
      "source": "dbt_project.yml",
      "target": "models/staging/stg_products.sql"
    },
    {
      "edge_type": "CONFIGURES",
      "weight": 1,
      "source": "dbt_project.yml",
      "target": "macros/generate_schema_name.sql"
    },
    {
      "edge_type": "CONFIGURES",
      "weight": 1,
      "source": "dbt_project.yml",
      "target": "models/marts/supplies.sql"
    },
    {
      "edge_type": "CONFIGURES",
      "weight": 1,
      "source": "dbt_project.yml",
      "target": "models/staging/stg_orders.sql"
    },
    {
      "edge_type": "CONFIGURES",
      "weight": 1,
      "source": "dbt_project.yml",
      "target": "models/staging/stg_supplies.sql"
    }
  ]
}